inference_models/__init__.py
inference_models/configuration.py
inference_models/constants.py
inference_models/developer_tools.py
inference_models/entities.py
inference_models/errors.py
inference_models/logger.py
inference_models/model_pipelines/__init__.py
inference_models/model_pipelines/auto_loaders/__init__.py
inference_models/model_pipelines/auto_loaders/core.py
inference_models/model_pipelines/auto_loaders/pipelines_registry.py
inference_models/model_pipelines/face_and_gaze_detection/__init__.py
inference_models/model_pipelines/face_and_gaze_detection/mediapipe_l2cs.py
inference_models/models/__init__.py
inference_models/models/auto_loaders/__init__.py
inference_models/models/auto_loaders/access_manager.py
inference_models/models/auto_loaders/auto_negotiation.py
inference_models/models/auto_loaders/auto_resolution_cache.py
inference_models/models/auto_loaders/constants.py
inference_models/models/auto_loaders/core.py
inference_models/models/auto_loaders/dependency_models.py
inference_models/models/auto_loaders/entities.py
inference_models/models/auto_loaders/models_registry.py
inference_models/models/auto_loaders/presentation_utils.py
inference_models/models/auto_loaders/ranking.py
inference_models/models/auto_loaders/utils.py
inference_models/models/base/__init__.py
inference_models/models/base/classification.py
inference_models/models/base/depth_estimation.py
inference_models/models/base/documents_parsing.py
inference_models/models/base/embeddings.py
inference_models/models/base/instance_segmentation.py
inference_models/models/base/keypoints_detection.py
inference_models/models/base/object_detection.py
inference_models/models/base/semantic_segmentation.py
inference_models/models/base/types.py
inference_models/models/clip/__init__.py
inference_models/models/clip/clip_onnx.py
inference_models/models/clip/clip_pytorch.py
inference_models/models/clip/preprocessing.py
inference_models/models/common/__init__.py
inference_models/models/common/cuda.py
inference_models-0.18.5.dist-info/METADATA
inference_models-0.18.5.dist-info/WHEEL
inference_models-0.18.5.dist-info/top_level.txt
inference_models-0.18.5.dist-info/RECORD
